qkdpy/__init__.py
qkdpy/core/__init__.py
qkdpy/core/channels.py
qkdpy/core/detector.py
qkdpy/core/extended_channels.py
qkdpy/core/gate_utils.py
qkdpy/core/gates.py
qkdpy/core/measurements.py
qkdpy/core/multiqubit.py
qkdpy/core/photon_source.py
qkdpy/core/qubit.py
qkdpy/core/qudit.py
qkdpy/core/security_analysis.py
qkdpy/core/timing.py
qkdpy/crypto/__init__.py
qkdpy/crypto/advanced_crypto.py
qkdpy/crypto/authentication.py
qkdpy/crypto/decryption.py
qkdpy/crypto/encryption.py
qkdpy/crypto/enhanced_security.py
qkdpy/crypto/key_exchange.py
qkdpy/crypto/quantum_auth.py
qkdpy/crypto/quantum_rng.py
qkdpy/integrations/__init__.py
qkdpy/integrations/cirq_integration.py
qkdpy/integrations/pennylane_integration.py
qkdpy/integrations/qiskit_integration.py
qkdpy/key_management/__init__.py
qkdpy/key_management/advanced_error_correction.py
qkdpy/key_management/advanced_privacy_amplification.py
qkdpy/key_management/error_correction.py
qkdpy/key_management/key_distillation.py
qkdpy/key_management/key_manager.py
qkdpy/key_management/privacy_amplification.py
qkdpy/key_management/quantum_error_correction.py
qkdpy/ml/__init__.py
qkdpy/ml/qkd_optimizer.py
qkdpy/network/__init__.py
qkdpy/network/multiparty_qkd.py
qkdpy/network/quantum_network.py
qkdpy/network/realistic_quantum_network.py
qkdpy/protocols/__init__.py
qkdpy/protocols/b92.py
qkdpy/protocols/base.py
qkdpy/protocols/bb84.py
qkdpy/protocols/cv_qkd.py
qkdpy/protocols/decoy_state_bb84.py
qkdpy/protocols/di_qkd.py
qkdpy/protocols/e91.py
qkdpy/protocols/enhanced_cv_qkd.py
qkdpy/protocols/hd_qkd.py
qkdpy/protocols/sarg04.py
qkdpy/protocols/twisted_pair.py
qkdpy/utils/__init__.py
qkdpy/utils/advanced_quantum_visualization.py
qkdpy/utils/advanced_visualization.py
qkdpy/utils/helpers.py
qkdpy/utils/quantum_simulator.py
qkdpy/utils/visualization.py
qkdpy-0.2.9.dist-info/licenses/LICENSE
qkdpy-0.2.9.dist-info/METADATA
qkdpy-0.2.9.dist-info/WHEEL
qkdpy-0.2.9.dist-info/top_level.txt
qkdpy-0.2.9.dist-info/RECORD
