Metadata-Version: 2.4
Name: qkdpy
Version: 0.2.9
Summary: A Python Package for Quantum Key Distribution
Author-email: Pranava-Kumar <pranavakumar.it@gmail.com>
Maintainer-email: Pranava-Kumar <pranavakumar.it@gmail.com>
License-Expression: Apache-2.0
Project-URL: Homepage, https://github.com/Pranava-Kumar/qkdpy
Project-URL: Repository, https://github.com/Pranava-Kumar/qkdpy
Project-URL: Bug Tracker, https://github.com/Pranava-Kumar/qkdpy/issues
Keywords: quantum,cryptography,qkd,simulation,hd-qkd,quantum-networks
Classifier: Development Status :: 3 - Alpha
Classifier: Intended Audience :: Developers
Classifier: Intended Audience :: Science/Research
Classifier: Operating System :: OS Independent
Classifier: Programming Language :: Python :: 3
Classifier: Programming Language :: Python :: 3.10
Classifier: Programming Language :: Python :: 3.11
Classifier: Programming Language :: Python :: 3.12
Classifier: Topic :: Scientific/Engineering :: Physics
Classifier: Topic :: Security :: Cryptography
Requires-Python: >=3.10
License-File: LICENSE
Requires-Dist: numpy>=1.24.0
Requires-Dist: matplotlib>=3.7.0
Requires-Dist: scipy>=1.10.0
Provides-Extra: dev
Requires-Dist: pytest>=7.0.0; extra == "dev"
Requires-Dist: pytest-cov>=4.0.0; extra == "dev"
Requires-Dist: black>=25.1.0; extra == "dev"
Requires-Dist: bandit>=1.8.6; extra == "dev"
Requires-Dist: mypy>=1.17.1; extra == "dev"
Requires-Dist: ruff>=0.12.8; extra == "dev"
Requires-Dist: isort>=6.0.1; extra == "dev"
Requires-Dist: hatchling>=1.27.0; extra == "dev"
Requires-Dist: pre-commit>=3.0.0; extra == "dev"
Requires-Dist: sphinx>=6.0.0; extra == "dev"
Requires-Dist: sphinx-rtd-theme>=1.2.0; extra == "dev"
Requires-Dist: twine>=4.0.0; extra == "dev"
Requires-Dist: build>=0.10.0; extra == "dev"
Provides-Extra: ml
Requires-Dist: scikit-learn>=1.3.0; extra == "ml"
Requires-Dist: pandas>=2.0.0; extra == "ml"
Provides-Extra: docs
Requires-Dist: sphinx>=6.0.0; extra == "docs"
Requires-Dist: sphinx-rtd-theme>=1.2.0; extra == "docs"
Requires-Dist: myst-parser>=1.0.0; extra == "docs"
Provides-Extra: viz
Requires-Dist: seaborn>=0.12.0; extra == "viz"
Dynamic: license-file
